wex/__init__.py
wex/client.py
wex_api-0.1.7.dist-info/DESCRIPTION.rst
wex_api-0.1.7.dist-info/METADATA
wex_api-0.1.7.dist-info/RECORD
wex_api-0.1.7.dist-info/WHEEL
wex_api-0.1.7.dist-info/metadata.json
wex_api-0.1.7.dist-info/top_level.txt
