Metadata-Version: 2.0
Name: wex-api
Version: 0.1.7
Summary: wex.nz exchange API client
Home-page: https://github.com/qweeze/wex-api-client
Author: qweeze
Author-email: qweeeze@gmail.com
License: UNKNOWN
Platform: UNKNOWN
